gen_ui_kit/GenUIKit.py
gen_ui_kit/GenUIKitPrompts.py
gen_ui_kit/GenUIKitTools.py
gen_ui_kit/__init__.py
gen_ui_kit/utils.py
gen_ui_kit-0.1.1.dist-info/LICENSE
gen_ui_kit-0.1.1.dist-info/METADATA
gen_ui_kit-0.1.1.dist-info/WHEEL
gen_ui_kit-0.1.1.dist-info/top_level.txt
gen_ui_kit-0.1.1.dist-info/RECORD
