Metadata-Version: 2.1
Name: gen-ui-kit
Version: 0.1.1
Summary: Gen-UI-Kit is a developer tool that generates starter web UI kits based on project ideas and descriptions. Leveraging LangChain and Cloudscape Design System, it simplifies the process of starting a project by providing a customizable UI kit. Developers can easily connect the generated kit to their APIs or backends, accelerating the early stages of development for new apps or front-end interfaces.
Home-page: https://github.com/makkzone/Gen-UI-Kit
Author: Manojkumar Kotakonda
Author-email: manojkumar.kotakonda@gmail.com
License: MIT License
Classifier: Programming Language :: Python :: 3.10
Classifier: Operating System :: OS Independent
Requires-Python: >=3.10
License-File: LICENSE
Requires-Dist: langchain==0.3.2
Requires-Dist: gitpython==3.1.43
